[1,["d5HhHjKDlGbIUvxF+AMzVi","23QJXS6SlKc5m4+pycxy2y","69sU0beMZK04QFMIvYYZGo","657mX5U1hH75f8C079NhjB"],["_textureSetter","_effectAsset"],["cc.SpriteFrame",["cc.Material",["_name","_techniqueData"],1]],[[1,0,1,3]],[[[{"name":"slime_114_38_3","rect":[0,0,152,128],"offset":[0,0],"originalSize":[152,128],"capInsets":[0,0,0,0]}],[0],0,[0],[0],[0]],[[[0,"eff_smooth_pro_mat__38_32",{"0":{"defines":{},"props":{"textureWidth":38,"textureHeight":32}}}]],0,0,[0],[1],[1]],[[{"name":"slime_112_38_1","rect":[0,0,152,128],"offset":[0,0],"originalSize":[152,128],"capInsets":[0,0,0,0]}],[0],0,[0],[0],[2]],[[{"name":"slime_113_38_2","rect":[0,0,152,128],"offset":[0,0],"originalSize":[152,128],"capInsets":[0,0,0,0]}],[0],0,[0],[0],[3]]]]